telamonpypi/__init__.py
telamonpypi/telamonpypi.py
telamonpypi-1.0.2.dist-info/LICENSE
telamonpypi-1.0.2.dist-info/METADATA
telamonpypi-1.0.2.dist-info/WHEEL
telamonpypi-1.0.2.dist-info/top_level.txt
telamonpypi-1.0.2.dist-info/RECORD
