Metadata-Version: 2.1
Name: telamonpypi
Version: 1.0.2
Summary: TelamonPypi is a python package to scan ports with just 2 lines of code.
Home-page: https://acnsoft.net/telamonpypi.html
Author: AcnSoft
Author-email: info@acnsoft.net
Classifier: Programming Language :: Python :: 3
Classifier: License :: OSI Approved :: MIT License
Classifier: Operating System :: OS Independent
License-File: LICENSE
